farq/__init__.py
farq/analysis.py
farq/core.py
farq/indices.py
farq/ml.py
farq/utils.py
farq/visualization.py
farq-0.1.5.1.dist-info/LICENSE
farq-0.1.5.1.dist-info/METADATA
farq-0.1.5.1.dist-info/WHEEL
farq-0.1.5.1.dist-info/top_level.txt
farq-0.1.5.1.dist-info/RECORD
